leaptask/__init__.py
leaptask/base.py
leaptask/base_g.py
leaptask/demo2.py
leaptask/demobase.py
leaptask/faceAI.py
leaptask/l2_unit1.py
leaptask/task001.py
leaptask/task002.py
leaptask/task101.py
leaptask/PythonL11V1/__init__.py
leaptask/PythonL11V1/bdqxbase.py
leaptask/PythonL11V1/gardenbase.py
leaptask/PythonL11V1/gardenbase2.py
leaptask/PythonL11V1/rainbowbase.py
leaptask/PythonL11V1/schoolbusbase.py
leaptask/PythonL11V1/sunflowerbase.py
leaptask/PythonL31V1/__init__.py
leaptask/PythonL31V1/peacebase.py
leaptask-2022.4.2.dist-info/METADATA
leaptask-2022.4.2.dist-info/WHEEL
leaptask-2022.4.2.dist-info/top_level.txt
leaptask-2022.4.2.dist-info/RECORD
