Metadata-Version: 2.1
Name: leaptask
Version: 2022.4.2
Summary: leap task
Home-page: http://github.com/XRDX/pyleap
Author: Vic Wang
Author-email: 305880887@qq.com
License: UNKNOWN
Platform: UNKNOWN
Classifier: Programming Language :: Python :: 3
Classifier: License :: OSI Approved :: BSD License
Classifier: Operating System :: OS Independent
